loopdetect/__init__.py
loopdetect/core.py
loopdetect/examples.py
loopdetect/data/li08_solution.tsv
loopdetect-0.1.0.dist-info/LICENSE
loopdetect-0.1.0.dist-info/METADATA
loopdetect-0.1.0.dist-info/WHEEL
loopdetect-0.1.0.dist-info/top_level.txt
loopdetect-0.1.0.dist-info/RECORD
