Metadata-Version: 2.1
Name: loopdetect
Version: 0.1.0
Summary: A Python package for feedback loop detection in ODE models
Home-page: https://gitlab.com/kabaum/loopdetect
Author: Katharina Baum
Author-email: katharina.baum@hpi.de
License: BSD
Project-URL: Documentation, https://kabaum.gitlab.io/loopdetect
Platform: UNKNOWN
Classifier: Intended Audience :: Science/Research
Classifier: License :: OSI Approved :: BSD License
Classifier: Programming Language :: Python :: 3
Classifier: Programming Language :: Python :: 3.8
Requires-Dist: pandas
Requires-Dist: numpy
Requires-Dist: numdifftools
Requires-Dist: networkx
Requires-Dist: setuptools
